setup.py
moonshine/__init__.py
moonshine/auth.py
moonshine/db.py
moonshine_node.egg-info/PKG-INFO
moonshine_node.egg-info/SOURCES.txt
moonshine_node.egg-info/dependency_links.txt
moonshine_node.egg-info/requires.txt
moonshine_node.egg-info/top_level.txt