Metadata-Version: 2.1
Name: moonshine-node
Version: 0.0.8
Summary: toolkit for moonshine node-server
Home-page: https://github.com/MoonShineVFX/node-package
Author: eli Hung
Author-email: mrhchief@gmail.com
License: UNKNOWN
Platform: UNKNOWN
Classifier: Programming Language :: Python :: 3
Classifier: License :: OSI Approved :: MIT License
Classifier: Operating System :: OS Independent
Requires-Python: >=3.6
